CHANGELOG.md
LICENSE
MANIFEST.in
README.md
pyproject.toml
setup.cfg
setup.py
pyrelic/__init__.py
pyrelic/_relic.pxd
pyrelic/_relic.pyi
pyrelic/_relic.pyx
pyrelic/additive.py
pyrelic/py.typed
pyrelic/relic.pxd
python_relic.egg-info/PKG-INFO
python_relic.egg-info/SOURCES.txt
python_relic.egg-info/dependency_links.txt
python_relic.egg-info/not-zip-safe
python_relic.egg-info/top_level.txt