Metadata-Version: 2.1
Name: python-relic
Version: 0.1.1
Summary: Python bindings for the relic toolkit
Home-page: https://github.com/sebastinas/pyrelic
Author: Sebastian Ramacher
Author-email: sebastian.ramacher@ait.ac.at
License: MIT
Platform: UNKNOWN
Classifier: Development Status :: 4 - Beta
Classifier: Intended Audience :: Developers
Classifier: License :: OSI Approved :: MIT License
Classifier: Programming Language :: Python :: 3
Classifier: Topic :: Software Development :: Libraries :: Python Modules
Requires-Python: >=3.6
